.travis.yml
AUTHORS
ChangeLog
LICENSE
README.rst
requirements.txt
setup.cfg
setup.py
test-requirements.txt
tox.ini
tests/__init__.py
tests/test_api.py
tests/test_remote.py
tests/test_router.py
tests/test_server.py
tests/Integration/__init__.py
tests/Integration/test_router_ubersmith_core.py
ubersmith_remote_module_server/__init__.py
ubersmith_remote_module_server/api.py
ubersmith_remote_module_server/exceptions.py
ubersmith_remote_module_server/objects.py
ubersmith_remote_module_server/remote.py
ubersmith_remote_module_server/router.py
ubersmith_remote_module_server/server.py
ubersmith_remote_module_server.egg-info/PKG-INFO
ubersmith_remote_module_server.egg-info/SOURCES.txt
ubersmith_remote_module_server.egg-info/dependency_links.txt
ubersmith_remote_module_server.egg-info/not-zip-safe
ubersmith_remote_module_server.egg-info/pbr.json
ubersmith_remote_module_server.egg-info/requires.txt
ubersmith_remote_module_server.egg-info/top_level.txt