Metadata-Version: 1.1
Name: ubersmith-remote-module-server
Version: 1.1.0
Summary: A ubersmith remote module server
Home-page: UNKNOWN
Author: Internap
Author-email: opensource@internap.com
License: UNKNOWN
Platform: UNKNOWN
Classifier: Development Status :: 5 - Production/Stable
Classifier: Intended Audience :: Developers
Classifier: License :: OSI Approved :: Apache Software License
Classifier: Operating System :: POSIX
Classifier: Programming Language :: Python :: 2.7
Classifier: Programming Language :: Python :: 3.4
